setup.py
aojtools/__init__.py
aojtools/generated.py
aojtools/libxmlload.py
aojtools/parse.py
aojtools/settings.py
aojtools/submit.py
aojtools.egg-info/PKG-INFO
aojtools.egg-info/SOURCES.txt
aojtools.egg-info/dependency_links.txt
aojtools.egg-info/top_level.txt
scripts/aojcategories
scripts/aojprepare
scripts/aojrun
scripts/aojsolvedlist
scripts/aojsubmit