Metadata-Version: 1.1
Name: aojtools
Version: 0.2.2
Summary: api client library and scripts for aizu online judge system.
Home-page: https://github.com/yatt/aojtools
Author: yatt
Author-email: darknesssharp@gmail.com
License: MIT
Keywords: competitive programming
Platform: UNKNOWN
Classifier: Programming Language :: Python
Classifier: Topic :: Internet :: WWW/HTTP
Classifier: Topic :: Software Development :: Libraries :: Python Modules
